{
	"generalInfo": {
		"Category": "Business Node",
		"RequiredCoreLevel": "1",
		"AdditionalNodes": "3 - 6 - 11",
		"NodeConnections": "3",
		"ProgramSlots": "3",
		"Type": "Resource Node",
		"RegenerationRate": "2%"
	},
    "1": {
        "Firewall": "150",
        "ProductionLimit(total)": "24",
        "ProductionSpeed(hourly)": "16",
        "ProductiveIdleTime(hours)": "1.5Hours",
        "Transferpersecond": "1",
        "TimefromFullCapacity": "7.19Seconds",
        "Percent(persecond)": "13.9%",
        "UpgradeCost": "$250",
        "ExperienceGained": "50",
        "CompletionTime": "1Minute",
        "RequiredCoreLevel": "1",
        "imageAddress": "https://static.wikia.nocookie.net/hackersthegame/images/e/e9/B-coin_Mine_01.png/revision/latest/scale-to-width-down/135?cb=20170316221657"
    },
    "2": {
        "Firewall": "165",
        "ProductionLimit(total)": "48",
        "ProductionSpeed(hourly)": "24",
        "ProductiveIdleTime(hours)": "2Hours",
        "Transferpersecond": "1",
        "TimefromFullCapacity": "14.4Seconds",
        "Percent(persecond)": "6.94%",
        "UpgradeCost": "$500",
        "ExperienceGained": "100",
        "CompletionTime": "5Minutes",
        "RequiredCoreLevel": "2",
        "imageAddress": "https://static.wikia.nocookie.net/hackersthegame/images/3/33/B-coin_Mine_02-03.png/revision/latest/scale-to-width-down/135?cb=20170316222446"
    },
    "3": {
        "Firewall": "185",
        "ProductionLimit(total)": "72",
        "ProductionSpeed(hourly)": "32",
        "ProductiveIdleTime(hours)": "2.25Hours",
        "Transferpersecond": "2",
        "TimefromFullCapacity": "10.8Seconds",
        "Percent(persecond)": "9.26%",
        "UpgradeCost": "$1,000",
        "ExperienceGained": "200",
        "CompletionTime": "1Hour",
        "RequiredCoreLevel": "2",
        "imageAddress": "https://static.wikia.nocookie.net/hackersthegame/images/3/33/B-coin_Mine_02-03.png/revision/latest/scale-to-width-down/135?cb=20170316222446"
    },
    "4": {
        "Firewall": "205",
        "ProductionLimit(total)": "192",
        "ProductionSpeed(hourly)": "42",
        "ProductiveIdleTime(hours)": "~4.57Hours",
        "Transferpersecond": "3",
        "TimefromFullCapacity": "19.2Seconds",
        "Percent(persecond)": "5.21%",
        "UpgradeCost": "$2,000",
        "ExperienceGained": "300",
        "CompletionTime": "4Hours",
        "RequiredCoreLevel": "2",
        "imageAddress": "https://static.wikia.nocookie.net/hackersthegame/images/e/e9/B-coin_Mine_04-05.png/revision/latest/scale-to-width-down/135?cb=20170316222513"
    },
    "5": {
        "Firewall": "230",
        "ProductionLimit(total)": "252",
        "ProductionSpeed(hourly)": "52",
        "ProductiveIdleTime(hours)": "~4.85Hours",
        "Transferpersecond": "4",
        "TimefromFullCapacity": "18.9Seconds",
        "Percent(persecond)": "5.29%",
        "UpgradeCost": "$4,000",
        "ExperienceGained": "375",
        "CompletionTime": "6Hours",
        "RequiredCoreLevel": "2",
        "imageAddress": "https://static.wikia.nocookie.net/hackersthegame/images/e/e9/B-coin_Mine_04-05.png/revision/latest/scale-to-width-down/135?cb=20170316222513"
    },
    "6": {
        "Firewall": "255",
        "ProductionLimit(total)": "384",
        "ProductionSpeed(hourly)": "64",
        "ProductiveIdleTime(hours)": "6Hours",
        "Transferpersecond": "5",
        "TimefromFullCapacity": "23.0Seconds",
        "Percent(persecond)": "4.34%",
        "UpgradeCost": "$8,000",
        "ExperienceGained": "450",
        "CompletionTime": "12Hours",
        "RequiredCoreLevel": "3",
        "imageAddress": "https://static.wikia.nocookie.net/hackersthegame/images/b/bb/B-coin_Mine_06-07.png/revision/latest/scale-to-width-down/135?cb=20170316222539"
    },
    "7": {
        "Firewall": "280",
        "ProductionLimit(total)": "912",
        "ProductionSpeed(hourly)": "76",
        "ProductiveIdleTime(hours)": "12Hours",
        "Transferpersecond": "11",
        "TimefromFullCapacity": "24.9Seconds",
        "Percent(persecond)": "4.02%",
        "UpgradeCost": "$16,000",
        "ExperienceGained": "475",
        "CompletionTime": "18Hours",
        "RequiredCoreLevel": "3",
        "imageAddress": "https://static.wikia.nocookie.net/hackersthegame/images/b/bb/B-coin_Mine_06-07.png/revision/latest/scale-to-width-down/135?cb=20170316222539"
    },
    "8": {
        "Firewall": "310",
        "ProductionLimit(total)": "1,056",
        "ProductionSpeed(hourly)": "88",
        "ProductiveIdleTime(hours)": "12Hours",
        "Transferpersecond": "12",
        "TimefromFullCapacity": "26.4Seconds",
        "Percent(persecond)": "3.79%",
        "UpgradeCost": "$32,000",
        "ExperienceGained": "500",
        "CompletionTime": "24Hours",
        "RequiredCoreLevel": "4",
        "imageAddress": "https://static.wikia.nocookie.net/hackersthegame/images/a/a9/B-coin_Mine_08-09.png/revision/latest/scale-to-width-down/135?cb=20170316222603"
    },
    "9": {
        "Firewall": "345",
        "ProductionLimit(total)": "1,260",
        "ProductionSpeed(hourly)": "105",
        "ProductiveIdleTime(hours)": "12Hours",
        "Transferpersecond": "14",
        "TimefromFullCapacity": "27.0Seconds",
        "Percent(persecond)": "3.70%",
        "UpgradeCost": "$64,000",
        "ExperienceGained": "575",
        "CompletionTime": "30Hours",
        "RequiredCoreLevel": "4",
        "imageAddress": "https://static.wikia.nocookie.net/hackersthegame/images/a/a9/B-coin_Mine_08-09.png/revision/latest/scale-to-width-down/135?cb=20170316222603"
    },
    "10": {
        "Firewall": "385",
        "ProductionLimit(total)": "1,440",
        "ProductionSpeed(hourly)": "120",
        "ProductiveIdleTime(hours)": "12Hours",
        "Transferpersecond": "15",
        "TimefromFullCapacity": "28.8Seconds",
        "Percent(persecond)": "3.47%",
        "UpgradeCost": "$128,000",
        "ExperienceGained": "650",
        "CompletionTime": "36Hours",
        "RequiredCoreLevel": "5",
        "imageAddress": "https://static.wikia.nocookie.net/hackersthegame/images/c/c2/B-coin_Mine_10-12.png/revision/latest/scale-to-width-down/135?cb=20170316222630"
    },
    "11": {
        "Firewall": "425",
        "ProductionLimit(total)": "3,120",
        "ProductionSpeed(hourly)": "130",
        "ProductiveIdleTime(hours)": "24Hours",
        "Transferpersecond": "31",
        "TimefromFullCapacity": "30.2Seconds",
        "Percent(persecond)": "3.31%",
        "UpgradeCost": "$200,000",
        "ExperienceGained": "725",
        "CompletionTime": "42Hours",
        "RequiredCoreLevel": "5",
        "imageAddress": "https://static.wikia.nocookie.net/hackersthegame/images/c/c2/B-coin_Mine_10-12.png/revision/latest/scale-to-width-down/135?cb=20170316222630"
    },
    "12": {
        "Firewall": "470",
        "ProductionLimit(total)": "3,600",
        "ProductionSpeed(hourly)": "150",
        "ProductiveIdleTime(hours)": "24Hours",
        "Transferpersecond": "34",
        "TimefromFullCapacity": "31.8Seconds",
        "Percent(persecond)": "3.15%",
        "UpgradeCost": "$250,000",
        "ExperienceGained": "800",
        "CompletionTime": "48Hours",
        "RequiredCoreLevel": "6",
        "imageAddress": "https://static.wikia.nocookie.net/hackersthegame/images/c/c2/B-coin_Mine_10-12.png/revision/latest/scale-to-width-down/135?cb=20170316222630"
    },
    "13": {
        "Firewall": "525",
        "ProductionLimit(total)": "4,320",
        "ProductionSpeed(hourly)": "180",
        "ProductiveIdleTime(hours)": "24Hours",
        "Transferpersecond": "39",
        "TimefromFullCapacity": "33.2Seconds",
        "Percent(persecond)": "3.01%",
        "UpgradeCost": "$300,000",
        "ExperienceGained": "850",
        "CompletionTime": "60Hours",
        "RequiredCoreLevel": "6",
        "imageAddress": "https://static.wikia.nocookie.net/hackersthegame/images/9/9c/B-coin_Mine_13-15.png/revision/latest/scale-to-width-down/135?cb=20170316222652"
    },
    "14": {
        "Firewall": "580",
        "ProductionLimit(total)": "5,040",
        "ProductionSpeed(hourly)": "210",
        "ProductiveIdleTime(hours)": "24Hours",
        "Transferpersecond": "43",
        "TimefromFullCapacity": "35.2Seconds",
        "Percent(persecond)": "2.84%",
        "UpgradeCost": "$400,000",
        "ExperienceGained": "900",
        "CompletionTime": "72Hours",
        "RequiredCoreLevel": "7",
        "imageAddress": "https://static.wikia.nocookie.net/hackersthegame/images/9/9c/B-coin_Mine_13-15.png/revision/latest/scale-to-width-down/135?cb=20170316222652"
    },
    "15": {
        "Firewall": "645",
        "ProductionLimit(total)": "8,000",
        "ProductionSpeed(hourly)": "250",
        "ProductiveIdleTime(hours)": "32Hours",
        "Transferpersecond": "64",
        "TimefromFullCapacity": "37.5Seconds",
        "Percent(persecond)": "2.67%",
        "UpgradeCost": "$500,000",
        "ExperienceGained": "950",
        "CompletionTime": "92Hours",
        "RequiredCoreLevel": "7",
        "imageAddress": "https://static.wikia.nocookie.net/hackersthegame/images/9/9c/B-coin_Mine_13-15.png/revision/latest/scale-to-width-down/135?cb=20170316222652"
    },
    "16": {
        "Firewall": "720",
        "ProductionLimit(total)": "9,600",
        "ProductionSpeed(hourly)": "300",
        "ProductiveIdleTime(hours)": "32Hours",
        "Transferpersecond": "72",
        "TimefromFullCapacity": "40.0Seconds",
        "Percent(persecond)": "2.50%",
        "UpgradeCost": "$550,000",
        "ExperienceGained": "1,000",
        "CompletionTime": "96Hours",
        "RequiredCoreLevel": "8",
        "imageAddress": "https://static.wikia.nocookie.net/hackersthegame/images/9/9d/B-coin_Mine_16-18.png/revision/latest/scale-to-width-down/135?cb=20170316222714"
    },
    "17": {
        "Firewall": "780",
        "ProductionLimit(total)": "11,200",
        "ProductionSpeed(hourly)": "350",
        "ProductiveIdleTime(hours)": "32Hours",
        "Transferpersecond": "80",
        "TimefromFullCapacity": "42.0Seconds",
        "Percent(persecond)": "2.38%",
        "UpgradeCost": "$600,000",
        "ExperienceGained": "1,080",
        "CompletionTime": "104Hours",
        "RequiredCoreLevel": "8",
        "imageAddress": "https://static.wikia.nocookie.net/hackersthegame/images/9/9d/B-coin_Mine_16-18.png/revision/latest/scale-to-width-down/135?cb=20170316222714"
    },
    "18": {
        "Firewall": "885",
        "ProductionLimit(total)": "14,500",
        "ProductionSpeed(hourly)": "450",
        "ProductiveIdleTime(hours)": "~32.2Hours",
        "Transferpersecond": "98",
        "TimefromFullCapacity": "44.1Seconds",
        "Percent(persecond)": "2.27%",
        "UpgradeCost": "$700,000",
        "ExperienceGained": "1,160",
        "CompletionTime": "112Hours",
        "RequiredCoreLevel": "9",
        "imageAddress": "https://static.wikia.nocookie.net/hackersthegame/images/9/9d/B-coin_Mine_16-18.png/revision/latest/scale-to-width-down/135?cb=20170316222714"
    },
    "19": {
        "Firewall": "980",
        "ProductionLimit(total)": "22,000",
        "ProductionSpeed(hourly)": "550",
        "ProductiveIdleTime(hours)": "40Hours",
        "Transferpersecond": "141",
        "TimefromFullCapacity": "46.8Seconds",
        "Percent(persecond)": "2.17%",
        "UpgradeCost": "$800,000",
        "ExperienceGained": "1,250",
        "CompletionTime": "120Hours",
        "RequiredCoreLevel": "9",
        "imageAddress": "https://static.wikia.nocookie.net/hackersthegame/images/b/b0/B-coin_Mine_19-21.png/revision/latest/scale-to-width-down/135?cb=20170316222742"
    },
    "20": {
        "Firewall": "1,090",
        "ProductionLimit(total)": "26,000",
        "ProductionSpeed(hourly)": "650",
        "ProductiveIdleTime(hours)": "40Hours",
        "Transferpersecond": "157",
        "TimefromFullCapacity": "49.6Seconds",
        "Percent(persecond)": "2.01%",
        "UpgradeCost": "$900,000",
        "ExperienceGained": "1,330",
        "CompletionTime": "128Hours",
        "RequiredCoreLevel": "9",
        "imageAddress": "https://static.wikia.nocookie.net/hackersthegame/images/b/b0/B-coin_Mine_19-21.png/revision/latest/scale-to-width-down/135?cb=20170316222742"
    },
    "21": {
        "Firewall": "1,210",
        "ProductionLimit(total)": "38,400",
        "ProductionSpeed(hourly)": "800",
        "ProductiveIdleTime(hours)": "48Hours",
        "Transferpersecond": "220",
        "TimefromFullCapacity": "52.4Seconds",
        "Percent(persecond)": "1.91%",
        "UpgradeCost": "$1,000,000",
        "ExperienceGained": "1,410",
        "CompletionTime": "136Hours",
        "RequiredCoreLevel": "9",
        "imageAddress": "https://static.wikia.nocookie.net/hackersthegame/images/b/b0/B-coin_Mine_19-21.png/revision/latest/scale-to-width-down/135?cb=20170316222742"
    }
}